arbitrary_inline/__init__.py
arbitrary_inline/admin.py
arbitrary_inline/forms.py
django_arbitrary_inline-0.1.2.dist-info/DESCRIPTION.rst
django_arbitrary_inline-0.1.2.dist-info/METADATA
django_arbitrary_inline-0.1.2.dist-info/metadata.json
django_arbitrary_inline-0.1.2.dist-info/RECORD
django_arbitrary_inline-0.1.2.dist-info/top_level.txt
django_arbitrary_inline-0.1.2.dist-info/WHEEL
